CHANGES.txt
DEPENDENCES.txt
README.txt
setup.py
src/ng/__init__.py
src/ng.kit.egg-info/PKG-INFO
src/ng.kit.egg-info/SOURCES.txt
src/ng.kit.egg-info/dependency_links.txt
src/ng.kit.egg-info/namespace_packages.txt
src/ng.kit.egg-info/not-zip-safe
src/ng.kit.egg-info/requires.txt
src/ng.kit.egg-info/top_level.txt
src/ng/kit/__init__.py
src/ng/kit/configure.zcml
src/ng/kit/ng.kit.txt
src/ng/kit/annotationremover/__init__.py
src/ng/kit/annotationremover/annotationremover.py
src/ng/kit/annotationremover/configure.zcml
src/ng/kit/annotationremover/interfaces.py
src/ng/kit/annotationremover/browser/__init__.py
src/ng/kit/annotationremover/browser/addform.pt
src/ng/kit/annotationremover/browser/configure.zcml
src/ng/kit/annotationremover/browser/editform.pt
src/ng/kit/annotationremover/browser/editform.py
src/ng/kit/etc/ng.kit-configure.zcml
src/ng/kit/fixintid/__init__.py
src/ng/kit/fixintid/configure.zcml
src/ng/kit/fixintid/fixintid.pt
src/ng/kit/fixintid/fixintid.py
src/ng/kit/fixintid/interfaces.py
src/ng/kit/fixparent/__init__.py
src/ng/kit/fixparent/configure.zcml
src/ng/kit/fixparent/fixparent.py
src/ng/kit/fixparent/interfaces.py
src/ng/kit/fixparent/browser/__init__.py
src/ng/kit/fixparent/browser/addform.pt
src/ng/kit/fixparent/browser/configure.zcml
src/ng/kit/fixparent/browser/editform.pt
src/ng/kit/fixparent/browser/editform.py
src/ng/kit/interfaceswitcher/__init__.py
src/ng/kit/interfaceswitcher/configure.zcml
src/ng/kit/interfaceswitcher/interfaces.py
src/ng/kit/interfaceswitcher/interfaceswitcher.py
src/ng/kit/interfaceswitcher/interfacevocabulary.py
